splupy2check/__init__.py
splupy2check/splupy2check.py
splupy2check-1.0.9.dist-info/LICENSE
splupy2check-1.0.9.dist-info/METADATA
splupy2check-1.0.9.dist-info/WHEEL
splupy2check-1.0.9.dist-info/entry_points.txt
splupy2check-1.0.9.dist-info/top_level.txt
splupy2check-1.0.9.dist-info/RECORD
