Metadata-Version: 2.1
Name: splupy2check
Version: 1.0.9
Summary: Scans file or folder to be scanned for containing Python 2 code.
Author: Sebastian Schimper
Author-email: sebastianschimper@gmail.com
Keywords: python,splunk,python2,scanning
Classifier: Development Status :: 1 - Planning
Classifier: Intended Audience :: Developers
Classifier: Programming Language :: Python :: 3
Classifier: Operating System :: Unix
Classifier: Operating System :: MacOS :: MacOS X
Classifier: Operating System :: Microsoft :: Windows
License-File: LICENSE
Requires-Dist: argparse
